torch_btg/__init__.py
torch_btg/confusion.py
torch_btg/loss.py
torch_btg/metric.py
torch_btg/tests/__init__.py
torch_btg/tests/test_metric.py
torch_btg-0.0.1.dist-info/METADATA
torch_btg-0.0.1.dist-info/WHEEL
torch_btg-0.0.1.dist-info/licenses/LICENSE
torch_btg-0.0.1.dist-info/RECORD
