Metadata-Version: 2.1
Name: torch-btg
Version: 0.0.1
Summary: Bridging the Gap: Unifying the Training and Evaluation of Neural Network Binary Classifiers
Project-URL: Homepage, https://btg.yale.edu
Project-URL: Bug Tracker, https://github.com/nathantsoi/torch-btg/issues
Author-email: Nathan Tsoi <nathan.tsoi@yale.edu>
License-File: LICENSE
Classifier: License :: OSI Approved :: BSD License
Classifier: Operating System :: OS Independent
Classifier: Programming Language :: Python :: 3
Requires-Python: >=3.6
Requires-Dist: numpy
Requires-Dist: torch
Provides-Extra: dev
Requires-Dist: bump2version; extra == 'dev'
Requires-Dist: pre-commit; extra == 'dev'
Requires-Dist: tox; extra == 'dev'
